{
  "getArtifact": {
    "script": "getArtifact.sh",
    "parameters": [
      "artifactID"
    ],
    "target": "deploy/chaordicledger-ipfs"
  },
  "getArtifactAtPath": {
    "script": "getArtifactAtPath.sh",
    "parameters": [
      "artifactPath"
    ],
    "directResult": "true",
    "target": "deploy/chaordicledger-ipfs"
  },
  "deleteArtifactAtPath": {
    "script": "deleteArtifactAtPath.sh",
    "parameters": [
      "artifactPath"
    ],
    "target": "deploy/chaordicledger-ipfs"
  },
  "createArtifact": {
    "script": "createArtifact.sh",
    "parameters": [
      "formData"
    ],
    "directResult": "true",
    "target": "deploy/org1-admin-cli"
  },
  "uploadArtifact": {
    "script": "uploadArtifact.sh",
    "parameters": [
      "artifactName",
      "file"
    ],
    "target": "deploy/org1-admin-cli"
  },
  "listArtifactsAtPath": {
    "script": "listArtifactsAtPath.sh",
    "parameters": [
      "path"
    ],
    "directResult": "true",
    "target": "deploy/chaordicledger-ipfs"
  },
  "listAllArtifacts": {
    "script": "listAllArtifacts.sh",
    "directResult": "true",
    "target": "deploy/org1-admin-cli"
  }
}
